[
    {
        "id": 1,
        "name": "Camiseta",
        "type": "Remeras",
        "price": 25000,
        "stock": 19,
        "description": "Remera Jordan mangas cortas talle 40",
        "Imagen": "./assets/Camiseta1.png"
    },
    {
        "id": 2,
        "name": "Jeans",
        "type": "Jeans",
        "price": 45000,
        "stock": 19,
        "description": "Jeans Levis talle 44",
        "Imagen": "./assets/Jeans2.png"
    },
    {
        "id": 3,
        "name": "Zapatillas",
        "type": "Calzado",
        "price": 59000,
        "stock": 19,
        "description": "Calzado urbano John Foos para uso diario talle 39",
        "Imagen": "./assets/Zapatillas3.png"
    },
    { 
        "id": 4,
        "name": "Gorra",
        "type": "Accesorios",
        "price": 21000,
        "stock": 19,
        "description": "Gorra NY de hilo y algodón talle universal",
        "Imagen": "./assets/Gorra4.png"
    }
]